odoo/addons/shopfloor_base/README.rst
odoo/addons/shopfloor_base/__init__.py
odoo/addons/shopfloor_base/__manifest__.py
odoo/addons/shopfloor_base/utils.py
odoo/addons/shopfloor_base/actions/__init__.py
odoo/addons/shopfloor_base/actions/base_action.py
odoo/addons/shopfloor_base/actions/data.py
odoo/addons/shopfloor_base/actions/data_detail.py
odoo/addons/shopfloor_base/actions/lock.py
odoo/addons/shopfloor_base/actions/message.py
odoo/addons/shopfloor_base/actions/savepoint.py
odoo/addons/shopfloor_base/actions/schema.py
odoo/addons/shopfloor_base/actions/schema_detail.py
odoo/addons/shopfloor_base/actions/search.py
odoo/addons/shopfloor_base/apispec/__init__.py
odoo/addons/shopfloor_base/apispec/service_apispec.py
odoo/addons/shopfloor_base/controllers/__init__.py
odoo/addons/shopfloor_base/controllers/api_docs.py
odoo/addons/shopfloor_base/controllers/main.py
odoo/addons/shopfloor_base/data/module_category_data.xml
odoo/addons/shopfloor_base/data/server_action.xml
odoo/addons/shopfloor_base/demo/res_users_demo.xml
odoo/addons/shopfloor_base/demo/shopfloor_menu_demo.xml
odoo/addons/shopfloor_base/demo/shopfloor_profile_demo.xml
odoo/addons/shopfloor_base/demo/shopfloor_scenario_demo.xml
odoo/addons/shopfloor_base/i18n/es_AR.po
odoo/addons/shopfloor_base/i18n/it.po
odoo/addons/shopfloor_base/i18n/shopfloor_base.pot
odoo/addons/shopfloor_base/migrations/14.0.2.9.0/post-migrate.py
odoo/addons/shopfloor_base/models/__init__.py
odoo/addons/shopfloor_base/models/ir_http.py
odoo/addons/shopfloor_base/models/shopfloor_app.py
odoo/addons/shopfloor_base/models/shopfloor_menu.py
odoo/addons/shopfloor_base/models/shopfloor_profile.py
odoo/addons/shopfloor_base/models/shopfloor_scenario.py
odoo/addons/shopfloor_base/readme/CONFIGURE.rst
odoo/addons/shopfloor_base/readme/CONTRIBUTORS.rst
odoo/addons/shopfloor_base/readme/CREDITS.rst
odoo/addons/shopfloor_base/readme/DESCRIPTION.rst
odoo/addons/shopfloor_base/readme/HISTORY.rst
odoo/addons/shopfloor_base/readme/ROADMAP.rst
odoo14_addon_shopfloor_base-14.0.2.12.0.dist-info/METADATA
odoo14_addon_shopfloor_base-14.0.2.12.0.dist-info/WHEEL
odoo14_addon_shopfloor_base-14.0.2.12.0.dist-info/top_level.txt
odoo14_addon_shopfloor_base-14.0.2.12.0.dist-info/RECORD
