Metadata-Version: 2.1
Name: odoo14-addon-shopfloor_base
Version: 14.0.2.12.0
Summary: Core module for creating mobile apps
Home-page: https://github.com/OCA/wms
Author: Camptocamp, BCIM, Akretion, Odoo Community Association (OCA)
Author-email: support@odoo-community.org
License: LGPL-3
Classifier: Programming Language :: Python
Classifier: Framework :: Odoo
Classifier: Framework :: Odoo :: 14.0
Classifier: License :: OSI Approved :: GNU Lesser General Public License v3 (LGPLv3)
Classifier: Development Status :: 4 - Beta
Requires-Python: >=3.6
Requires-Dist: odoo14-addon-base-rest
Requires-Dist: odoo14-addon-endpoint-route-handler
Requires-Dist: odoo14-addon-jsonifier
Requires-Dist: odoo<14.1dev,>=14.0a
